carver_feeds/__init__.py
carver_feeds/__version__.py
carver_feeds/carver_api.py
carver_feeds/data_manager.py
carver_feeds/py.typed
carver_feeds/query_engine.py
carver_feeds/s3_client.py
carver_feeds_sdk-0.3.0.dist-info/licenses/LICENSE
carver_feeds_sdk-0.3.0.dist-info/METADATA
carver_feeds_sdk-0.3.0.dist-info/WHEEL
carver_feeds_sdk-0.3.0.dist-info/top_level.txt
carver_feeds_sdk-0.3.0.dist-info/RECORD
