Metadata-Version: 2.4
Name: carver-feeds-sdk
Version: 0.3.0
Summary: Python SDK for the Carver Feeds API - fetch, analyze, and query regulatory feed data
Author-email: Carver Agents <support@carveragents.ai>
License: MIT
Project-URL: Homepage, https://github.com/carveragents/carver-feeds-sdk
Project-URL: Documentation, https://github.com/carveragents/carver-feeds-sdk/blob/master/README.md
Project-URL: Repository, https://github.com/carveragents/carver-feeds-sdk
Project-URL: Issues, https://github.com/carveragents/carver-feeds-sdk/issues
Keywords: carver,feeds,api,regulations,data,sdk,regulatory intelligence,risk management,real-time intelligence,risk assessment,compliance monitoring
Classifier: Development Status :: 4 - Beta
Classifier: Intended Audience :: Developers
Classifier: License :: OSI Approved :: MIT License
Classifier: Programming Language :: Python :: 3
Classifier: Programming Language :: Python :: 3.10
Classifier: Programming Language :: Python :: 3.11
Classifier: Programming Language :: Python :: 3.12
Classifier: Topic :: Software Development :: Libraries :: Python Modules
Classifier: Topic :: Internet :: WWW/HTTP :: Dynamic Content
Classifier: Typing :: Typed
Requires-Python: >=3.10
License-File: LICENSE
Requires-Dist: requests<3.0.0,>=2.31.0
Requires-Dist: pandas<3.0.0,>=2.0.0
Requires-Dist: numpy<2.0.0,>=1.24.0
Requires-Dist: pyarrow<19.0.0,>=14.0.0
Requires-Dist: python-dotenv<2.0.0,>=1.0.0
Requires-Dist: tqdm<5.0.0,>=4.65.0
Requires-Dist: tabulate<1.0.0,>=0.9.0
Requires-Dist: boto3<2.0.0,>=1.34.0
Provides-Extra: dev
Requires-Dist: pytest>=7.4.0; extra == "dev"
Requires-Dist: pytest-cov>=4.1.0; extra == "dev"
Requires-Dist: pytest-mock>=3.11.1; extra == "dev"
Requires-Dist: black>=23.7.0; extra == "dev"
Requires-Dist: ruff>=0.0.285; extra == "dev"
Requires-Dist: mypy>=1.4.1; extra == "dev"
Requires-Dist: types-requests>=2.31.0; extra == "dev"
Requires-Dist: types-tabulate>=0.9.0; extra == "dev"
Requires-Dist: build>=0.10.0; extra == "dev"
Requires-Dist: bumpversion>=0.6.0; extra == "dev"
Dynamic: license-file
